[
  {
    "ticker": "BWA",
    "period": "TTM 2025",
    "filing_date": "2026-02-11",
    "shares_outstanding": 216400000.0,
    "revenue": 14316000000.0,
    "net_income": 335000000.0,
    "market_cap": null
  },
  {
    "ticker": "BWA",
    "period": "FY 2025",
    "filing_date": "2026-02-11",
    "shares_outstanding": 216400000.0,
    "revenue": 14316000000.0,
    "net_income": 335000000.0,
    "market_cap": null
  },
  {
    "ticker": "BWA",
    "period": "Q3 2025",
    "filing_date": "2025-10-30",
    "shares_outstanding": 216500000.0,
    "revenue": 3591000000.0,
    "net_income": 173000000.0,
    "market_cap": null
  },
  {
    "ticker": "BWA",
    "period": "Q2 2025",
    "filing_date": "2025-07-31",
    "shares_outstanding": 218200000.0,
    "revenue": 3638000000.0,
    "net_income": 232000000.0,
    "market_cap": null
  },
  {
    "ticker": "BWA",
    "period": "Q1 2025",
    "filing_date": "2025-05-07",
    "shares_outstanding": 218100000.0,
    "revenue": 3515000000.0,
    "net_income": 171000000.0,
    "market_cap": null
  },
  {
    "ticker": "BWA",
    "period": "Q3 2024",
    "filing_date": "2024-10-31",
    "shares_outstanding": 224500000.0,
    "revenue": 3449000000.0,
    "net_income": 249000000.0,
    "market_cap": null
  },
  {
    "ticker": "BWA",
    "period": "Q2 2024",
    "filing_date": "2024-07-31",
    "shares_outstanding": 227200000.0,
    "revenue": 3603000000.0,
    "net_income": 317000000.0,
    "market_cap": null
  },
  {
    "ticker": "BWA",
    "period": "Q1 2024",
    "filing_date": "2024-05-02",
    "shares_outstanding": 228300000.0,
    "revenue": 3595000000.0,
    "net_income": 221000000.0,
    "market_cap": null
  },
  {
    "ticker": "BWA",
    "period": "FY 2023",
    "filing_date": "2024-02-08",
    "shares_outstanding": 234400000.0,
    "revenue": 14198000000.0,
    "net_income": 695000000.0,
    "market_cap": null
  },
  {
    "ticker": "BWA",
    "period": "Q3 2023",
    "filing_date": "2023-11-02",
    "shares_outstanding": 235300000.0,
    "revenue": 3622000000.0,
    "net_income": 68000000.0,
    "market_cap": null
  },
  {
    "ticker": "BWA",
    "period": "Q2 2023",
    "filing_date": "2023-08-02",
    "shares_outstanding": 234400000.0,
    "revenue": 4520000000.0,
    "net_income": 222000000.0,
    "market_cap": null
  },
  {
    "ticker": "BWA",
    "period": "Q1 2023",
    "filing_date": "2023-05-04",
    "shares_outstanding": 234400000.0,
    "revenue": 4180000000.0,
    "net_income": 230000000.0,
    "market_cap": null
  },
  {
    "ticker": "BWA",
    "period": "FY 2022",
    "filing_date": "2023-02-09",
    "shares_outstanding": 236800000.0,
    "revenue": 15801000000.0,
    "net_income": 1026000000.0,
    "market_cap": null
  },
  {
    "ticker": "BWA",
    "period": "Q3 2022",
    "filing_date": "2022-10-27",
    "shares_outstanding": 235600000.0,
    "revenue": 4060000000.0,
    "net_income": 292000000.0,
    "market_cap": null
  },
  {
    "ticker": "BWA",
    "period": "Q2 2022",
    "filing_date": "2022-08-03",
    "shares_outstanding": 238000000.0,
    "revenue": 3759000000.0,
    "net_income": 231000000.0,
    "market_cap": null
  },
  {
    "ticker": "BWA",
    "period": "Q1 2022",
    "filing_date": "2022-05-04",
    "shares_outstanding": 239000000.0,
    "revenue": 3874000000.0,
    "net_income": 224000000.0,
    "market_cap": null
  },
  {
    "ticker": "BWA",
    "period": "FY 2021",
    "filing_date": "2022-02-15",
    "shares_outstanding": 239500000.0,
    "revenue": 14838000000.0,
    "net_income": 639000000.0,
    "market_cap": null
  },
  {
    "ticker": "BWA",
    "period": "Q3 2021",
    "filing_date": "2021-11-03",
    "shares_outstanding": 239800000.0,
    "revenue": 3416000000.0,
    "net_income": 117000000.0,
    "market_cap": null
  },
  {
    "ticker": "BWA",
    "period": "Q2 2021",
    "filing_date": "2021-08-04",
    "shares_outstanding": 239600000.0,
    "revenue": 3758000000.0,
    "net_income": 274000000.0,
    "market_cap": null
  },
  {
    "ticker": "BWA",
    "period": "Q1 2021",
    "filing_date": "2021-05-05",
    "shares_outstanding": 238400000.0,
    "revenue": 4009000000.0,
    "net_income": 94000000.0,
    "market_cap": null
  },
  {
    "ticker": "BWA",
    "period": "FY 2020",
    "filing_date": "2021-02-22",
    "shares_outstanding": 214000000.0,
    "revenue": 10165000000.0,
    "net_income": 567000000.0,
    "market_cap": null
  },
  {
    "ticker": "BWA",
    "period": "Q3 2020",
    "filing_date": "2020-10-29",
    "shares_outstanding": 207300000.0,
    "revenue": 2534000000.0,
    "net_income": 129000000.0,
    "market_cap": null
  },
  {
    "ticker": "BWA",
    "period": "Q2 2020",
    "filing_date": "2020-08-05",
    "shares_outstanding": 206000000.0,
    "revenue": 1426000000.0,
    "net_income": -84000000.0,
    "market_cap": null
  },
  {
    "ticker": "BWA",
    "period": "Q1 2020",
    "filing_date": "2020-05-06",
    "shares_outstanding": 206200000.0,
    "revenue": 2279000000.0,
    "net_income": 137000000.0,
    "market_cap": null
  },
  {
    "ticker": "BWA",
    "period": "FY 2019",
    "filing_date": "2020-02-13",
    "shares_outstanding": 206800000.0,
    "revenue": 10168000000.0,
    "net_income": 797000000.0,
    "market_cap": null
  },
  {
    "ticker": "BWA",
    "period": "Q3 2019",
    "filing_date": "2019-10-31",
    "shares_outstanding": 206300000.0,
    "revenue": 2492000000.0,
    "net_income": 207000000.0,
    "market_cap": null
  },
  {
    "ticker": "BWA",
    "period": "Q2 2019",
    "filing_date": "2019-07-25",
    "shares_outstanding": 206800000.0,
    "revenue": 2551000000.0,
    "net_income": 182000000.0,
    "market_cap": null
  },
  {
    "ticker": "BWA",
    "period": "Q1 2019",
    "filing_date": "2019-04-25",
    "shares_outstanding": 207100000.0,
    "revenue": 2566000000.0,
    "net_income": 171000000.0,
    "market_cap": null
  },
  {
    "ticker": "BWA",
    "period": "FY 2018",
    "filing_date": "2019-02-19",
    "shares_outstanding": 209496000.0,
    "revenue": 10529600000.0,
    "net_income": 984600000.0,
    "market_cap": null
  },
  {
    "ticker": "BWA",
    "period": "Q3 2018",
    "filing_date": "2018-10-25",
    "shares_outstanding": 208738000.0,
    "revenue": 2478500000.0,
    "net_income": 215900000.0,
    "market_cap": null
  },
  {
    "ticker": "BWA",
    "period": "Q2 2018",
    "filing_date": "2018-07-26",
    "shares_outstanding": 209857000.0,
    "revenue": 2694000000.0,
    "net_income": 284300000.0,
    "market_cap": null
  },
  {
    "ticker": "BWA",
    "period": "Q1 2018",
    "filing_date": "2018-04-26",
    "shares_outstanding": 210766000.0,
    "revenue": 2784300000.0,
    "net_income": 236800000.0,
    "market_cap": null
  },
  {
    "ticker": "BWA",
    "period": "FY 2017",
    "filing_date": "2018-02-08",
    "shares_outstanding": 211548000.0,
    "revenue": 9799300000.0,
    "net_income": 483300000.0,
    "market_cap": null
  },
  {
    "ticker": "BWA",
    "period": "Q3 2017",
    "filing_date": "2017-10-26",
    "shares_outstanding": 211013000.0,
    "revenue": 2416200000.0,
    "net_income": 194600000.0,
    "market_cap": null
  },
  {
    "ticker": "BWA",
    "period": "Q2 2017",
    "filing_date": "2017-07-27",
    "shares_outstanding": 211478000.0,
    "revenue": 2389700000.0,
    "net_income": 221100000.0,
    "market_cap": null
  },
  {
    "ticker": "BWA",
    "period": "Q1 2017",
    "filing_date": "2017-04-27",
    "shares_outstanding": 212236000.0,
    "revenue": 2407000000.0,
    "net_income": 199600000.0,
    "market_cap": null
  },
  {
    "ticker": "BWA",
    "period": "FY 2016",
    "filing_date": "2017-02-09",
    "shares_outstanding": 215328000.0,
    "revenue": 9071000000.0,
    "net_income": 160200000.0,
    "market_cap": null
  },
  {
    "ticker": "BWA",
    "period": "Q3 2016",
    "filing_date": "2016-10-27",
    "shares_outstanding": 213766000.0,
    "revenue": 2214200000.0,
    "net_income": 93100000.0,
    "market_cap": null
  },
  {
    "ticker": "BWA",
    "period": "Q2 2016",
    "filing_date": "2016-07-28",
    "shares_outstanding": 216663000.0,
    "revenue": 2329200000.0,
    "net_income": 175400000.0,
    "market_cap": null
  },
  {
    "ticker": "BWA",
    "period": "Q1 2016",
    "filing_date": "2016-04-28",
    "shares_outstanding": 218137000.0,
    "revenue": 2268600000.0,
    "net_income": 173200000.0,
    "market_cap": null
  },
  {
    "ticker": "BWA",
    "period": "FY 2015",
    "filing_date": "2016-02-11",
    "shares_outstanding": 225648000.0,
    "revenue": 8023200000.0,
    "net_income": 646400000.0,
    "market_cap": null
  },
  {
    "ticker": "BWA",
    "period": "Q3 2015",
    "filing_date": "2015-10-29",
    "shares_outstanding": 225991000.0,
    "revenue": 1884000000.0,
    "net_income": 165900000.0,
    "market_cap": null
  },
  {
    "ticker": "BWA",
    "period": "Q2 2015",
    "filing_date": "2015-07-30",
    "shares_outstanding": 226615000.0,
    "revenue": 2031900000.0,
    "net_income": 157400000.0,
    "market_cap": null
  },
  {
    "ticker": "BWA",
    "period": "Q4 2015",
    "filing_date": "2015-04-30",
    "shares_outstanding": 227088000.0,
    "revenue": 1984200000.0,
    "net_income": 187700000.0,
    "market_cap": null
  },
  {
    "ticker": "BWA",
    "period": "FY 2014",
    "filing_date": "2015-02-12",
    "shares_outstanding": 228924000.0,
    "revenue": 8305100000.0,
    "net_income": 687500000.0,
    "market_cap": null
  },
  {
    "ticker": "BWA",
    "period": "Q3 2014",
    "filing_date": "2014-10-30",
    "shares_outstanding": 228668000.0,
    "revenue": 2032100000.0,
    "net_income": 173000000.0,
    "market_cap": null
  },
  {
    "ticker": "BWA",
    "period": "Q2 2014",
    "filing_date": "2014-07-31",
    "shares_outstanding": 229670000.0,
    "revenue": 2197000000.0,
    "net_income": 199900000.0,
    "market_cap": null
  },
  {
    "ticker": "BWA",
    "period": "Q1 2014",
    "filing_date": "2014-05-01",
    "shares_outstanding": 229327000.0,
    "revenue": 2084100000.0,
    "net_income": 167200000.0,
    "market_cap": null
  },
  {
    "ticker": "BWA",
    "period": "FY 2013",
    "filing_date": "2014-02-13",
    "shares_outstanding": 231337000.0,
    "revenue": 7436600000.0,
    "net_income": 651000000.0,
    "market_cap": null
  },
  {
    "ticker": "BWA",
    "period": "Q3 2013",
    "filing_date": "2013-10-30",
    "shares_outstanding": 115238000.0,
    "revenue": 1806200000.0,
    "net_income": 172900000.0,
    "market_cap": null
  },
  {
    "ticker": "BWA",
    "period": "Q2 2013",
    "filing_date": "2013-07-25",
    "shares_outstanding": 116101000.0,
    "revenue": 1893900000.0,
    "net_income": 180100000.0,
    "market_cap": null
  },
  {
    "ticker": "BWA",
    "period": "Q1 2013",
    "filing_date": "2013-04-25",
    "shares_outstanding": 116565000.0,
    "revenue": 1851100000.0,
    "net_income": 148600000.0,
    "market_cap": null
  },
  {
    "ticker": "BWA",
    "period": "FY 2012",
    "filing_date": "2013-02-14",
    "shares_outstanding": 121377000.0,
    "revenue": 7183200000.0,
    "net_income": 522400000.0,
    "market_cap": null
  },
  {
    "ticker": "BWA",
    "period": "Q3 2012",
    "filing_date": "2012-10-31",
    "shares_outstanding": 118499000.0,
    "revenue": 1695200000.0,
    "net_income": 105900000.0,
    "market_cap": null
  },
  {
    "ticker": "BWA",
    "period": "Q2 2012",
    "filing_date": "2012-07-26",
    "shares_outstanding": 121473000.0,
    "revenue": 1856400000.0,
    "net_income": 126200000.0,
    "market_cap": null
  },
  {
    "ticker": "BWA",
    "period": "Q1 2012",
    "filing_date": "2012-04-26",
    "shares_outstanding": 127742000.0,
    "revenue": 1912500000.0,
    "net_income": 163700000.0,
    "market_cap": null
  },
  {
    "ticker": "BWA",
    "period": "FY 2011",
    "filing_date": "2012-02-14",
    "shares_outstanding": 128468000.0,
    "revenue": 7114700000.0,
    "net_income": 570600000.0,
    "market_cap": null
  },
  {
    "ticker": "BWA",
    "period": "Q3 2011",
    "filing_date": "2011-10-28",
    "shares_outstanding": 127940000.0,
    "revenue": 1791800000.0,
    "net_income": 146700000.0,
    "market_cap": null
  },
  {
    "ticker": "BWA",
    "period": "Q2 2011",
    "filing_date": "2011-07-28",
    "shares_outstanding": 128142000.0,
    "revenue": 1818800000.0,
    "net_income": 167300000.0,
    "market_cap": null
  },
  {
    "ticker": "BWA",
    "period": "Q1 2011",
    "filing_date": "2011-04-28",
    "shares_outstanding": 130224000.0,
    "revenue": 1730400000.0,
    "net_income": 129400000.0,
    "market_cap": null
  },
  {
    "ticker": "BWA",
    "period": "FY 2010",
    "filing_date": "2011-02-10",
    "shares_outstanding": 129575000.0,
    "revenue": 5652800000.0,
    "net_income": 396200000.0,
    "market_cap": null
  },
  {
    "ticker": "BWA",
    "period": "Q3 2010",
    "filing_date": "2010-10-27",
    "shares_outstanding": 127804000.0,
    "revenue": 1410900000.0,
    "net_income": 111500000.0,
    "market_cap": null
  },
  {
    "ticker": "BWA",
    "period": "Q2 2010",
    "filing_date": "2010-07-30",
    "shares_outstanding": 129078000.0,
    "revenue": 1421700000.0,
    "net_income": 87700000.0,
    "market_cap": null
  },
  {
    "ticker": "BWA",
    "period": "Q1 2010",
    "filing_date": "2010-04-29",
    "shares_outstanding": 129663000.0,
    "revenue": 1286800000.0,
    "net_income": 81400000.0,
    "market_cap": null
  },
  {
    "ticker": "BWA",
    "period": "FY 2009",
    "filing_date": "2010-02-11",
    "shares_outstanding": 116939000.0,
    "revenue": 3961800000.0,
    "net_income": 36400000.0,
    "market_cap": null
  },
  {
    "ticker": "BWA",
    "period": "Q3 2009",
    "filing_date": "2009-10-28",
    "shares_outstanding": 117495000.0,
    "revenue": 1027800000.0,
    "net_income": 20000000.0,
    "market_cap": null
  },
  {
    "ticker": "BWA",
    "period": "Q2 2009",
    "filing_date": "2009-07-29",
    "shares_outstanding": 116564000.0,
    "revenue": 916200000.0,
    "net_income": -33900000.0,
    "market_cap": null
  }
]