[
  {
    "ticker": "ELF",
    "period": "Q3 2026",
    "announcement_date": null,
    "filing_date": "2026-02-05",
    "event_date": "2026-02-05",
    "eps_estimate": null,
    "eps_actual": null,
    "eps_surprise_pct": null,
    "revenue": 489505000.0,
    "net_income": 39376000.0,
    "shares_outstanding": 60190799.0,
    "ni_yoy_growth": 0.7277,
    "rev_yoy_growth": 0.486,
    "ni_qoq_growth": 2.5759,
    "ni_acceleration": 3.4923,
    "price_on_event_date": 76.86,
    "price_5d_after": 74.33,
    "price_20d_after": 82.44,
    "earn_ret_5d": -0.0335,
    "earn_ret_5d_to_20d": 0.1036
  },
  {
    "ticker": "ELF",
    "period": "Q2 2026",
    "announcement_date": null,
    "filing_date": "2025-11-10",
    "event_date": "2025-11-10",
    "eps_estimate": null,
    "eps_actual": null,
    "eps_surprise_pct": null,
    "revenue": 343936000.0,
    "net_income": 2996000.0,
    "shares_outstanding": 59593910.0,
    "ni_yoy_growth": -2.7646,
    "rev_yoy_growth": 0.0582,
    "ni_qoq_growth": -2.4086,
    "ni_acceleration": -2.9788,
    "price_on_event_date": 79.85,
    "price_5d_after": 72.79,
    "price_20d_after": 77.42,
    "earn_ret_5d": -0.0926,
    "earn_ret_5d_to_20d": 0.0617
  },
  {
    "ticker": "ELF",
    "period": "Q1 2026",
    "announcement_date": null,
    "filing_date": "2025-08-07",
    "event_date": "2025-08-07",
    "eps_estimate": null,
    "eps_actual": null,
    "eps_surprise_pct": null,
    "revenue": 353739000.0,
    "net_income": 33311000.0,
    "shares_outstanding": 57675035.0,
    "ni_yoy_growth": 0.2142,
    "rev_yoy_growth": 0.2667,
    "ni_qoq_growth": 0.6574,
    "ni_acceleration": 0.8704,
    "price_on_event_date": 99.92,
    "price_5d_after": 119.6,
    "price_20d_after": 133.97,
    "earn_ret_5d": 0.1798,
    "earn_ret_5d_to_20d": 0.1135
  },
  {
    "ticker": "ELF",
    "period": "Q3 2025",
    "announcement_date": "2025-02-06",
    "filing_date": "2025-02-07",
    "event_date": "2025-02-06",
    "eps_estimate": 0.75,
    "eps_actual": 0.74,
    "eps_surprise_pct": -0.0133,
    "revenue": 355320000.0,
    "net_income": 17261000.0,
    "shares_outstanding": 58353219.0,
    "ni_yoy_growth": -0.6562,
    "rev_yoy_growth": 0.5,
    "ni_qoq_growth": -0.097,
    "ni_acceleration": 0.3682,
    "price_on_event_date": 88.49,
    "price_5d_after": 74.95,
    "price_20d_after": 70.68,
    "earn_ret_5d": -0.1661,
    "earn_ret_5d_to_20d": -0.0587
  },
  {
    "ticker": "ELF",
    "period": "Q2 2025",
    "announcement_date": "2024-11-06",
    "filing_date": "2024-11-07",
    "event_date": "2024-11-06",
    "eps_estimate": 0.43,
    "eps_actual": 0.77,
    "eps_surprise_pct": 0.7907,
    "revenue": 301075000.0,
    "net_income": 19020000.0,
    "shares_outstanding": 58482530.0,
    "ni_yoy_growth": -1.0244,
    "rev_yoy_growth": 0.3305,
    "ni_qoq_growth": -0.9164,
    "ni_acceleration": -1.9363,
    "price_on_event_date": 104.16,
    "price_5d_after": 122.96,
    "price_20d_after": 131.23,
    "earn_ret_5d": 0.1659,
    "earn_ret_5d_to_20d": 0.0651
  },
  {
    "ticker": "ELF",
    "period": "Q1 2025",
    "announcement_date": "2024-08-08",
    "filing_date": "2024-08-09",
    "event_date": "2024-08-08",
    "eps_estimate": 0.84,
    "eps_actual": 1.1,
    "eps_surprise_pct": 0.3095,
    "revenue": 324477000.0,
    "net_income": 47555000.0,
    "shares_outstanding": 58551423.0,
    "ni_yoy_growth": 0.9119,
    "rev_yoy_growth": 0.7949,
    "ni_qoq_growth": 0.5702,
    "ni_acceleration": 0.0807,
    "price_on_event_date": 187.95,
    "price_5d_after": 155.54,
    "price_20d_after": 122.6,
    "earn_ret_5d": -0.1893,
    "earn_ret_5d_to_20d": -0.238
  },
  {
    "ticker": "ELF",
    "period": "Q3 2024",
    "announcement_date": "2024-02-06",
    "filing_date": "2024-02-07",
    "event_date": "2024-02-06",
    "eps_estimate": 0.56,
    "eps_actual": 0.74,
    "eps_surprise_pct": 0.3214,
    "revenue": 270943000.0,
    "net_income": 26888000.0,
    "shares_outstanding": 58030115.0,
    "ni_yoy_growth": 0.8312,
    "rev_yoy_growth": 0.795,
    "ni_qoq_growth": -0.213,
    "ni_acceleration": -0.0015,
    "price_on_event_date": 173.32,
    "price_5d_after": 167.86,
    "price_20d_after": 207.01,
    "earn_ret_5d": -0.032,
    "earn_ret_5d_to_20d": 0.2096
  },
  {
    "ticker": "ELF",
    "period": "Q2 2024",
    "announcement_date": "2023-11-01",
    "filing_date": "2023-11-02",
    "event_date": "2023-11-01",
    "eps_estimate": 0.53,
    "eps_actual": 0.82,
    "eps_surprise_pct": 0.5472,
    "revenue": 215507000.0,
    "net_income": 33271000.0,
    "shares_outstanding": 57438152.0,
    "ni_yoy_growth": 0.8327,
    "rev_yoy_growth": 0.5641,
    "ni_qoq_growth": -0.4652,
    "ni_acceleration": -1.3104,
    "price_on_event_date": 94.54,
    "price_5d_after": 98.14,
    "price_20d_after": 118.09,
    "earn_ret_5d": 0.0374,
    "earn_ret_5d_to_20d": 0.1851
  },
  {
    "ticker": "ELF",
    "period": "Q1 2024",
    "announcement_date": "2023-08-01",
    "filing_date": "2023-08-02",
    "event_date": "2023-08-01",
    "eps_estimate": 0.56,
    "eps_actual": 1.1,
    "eps_surprise_pct": 0.9643,
    "revenue": 216339000.0,
    "net_income": 52977000.0,
    "shares_outstanding": 57175870.0,
    "ni_yoy_growth": 2.1431,
    "rev_yoy_growth": 0.7907,
    "ni_qoq_growth": 1.0199,
    "ni_acceleration": 0.9378,
    "price_on_event_date": 116.5,
    "price_5d_after": 131.53,
    "price_20d_after": 133.63,
    "earn_ret_5d": 0.1213,
    "earn_ret_5d_to_20d": 0.0158
  },
  {
    "ticker": "ELF",
    "period": "Q3 2023",
    "announcement_date": "2023-02-01",
    "filing_date": "2023-02-02",
    "event_date": "2023-02-01",
    "eps_estimate": 0.23,
    "eps_actual": 0.48,
    "eps_surprise_pct": 1.087,
    "revenue": 146537000.0,
    "net_income": 19105000.0,
    "shares_outstanding": 55840137.0,
    "ni_yoy_growth": 1.2053,
    "rev_yoy_growth": 0.4671,
    "ni_qoq_growth": 0.4895,
    "ni_acceleration": 0.8582,
    "price_on_event_date": 58.51,
    "price_5d_after": 71.57,
    "price_20d_after": 75.22,
    "earn_ret_5d": 0.2015,
    "earn_ret_5d_to_20d": 0.0497
  },
  {
    "ticker": "ELF",
    "period": "Q2 2023",
    "announcement_date": "2022-11-02",
    "filing_date": "2022-11-03",
    "event_date": "2022-11-02",
    "eps_estimate": 0.16,
    "eps_actual": 0.36,
    "eps_surprise_pct": 1.25,
    "revenue": 122349000.0,
    "net_income": 11710000.0,
    "shares_outstanding": 55037514.0,
    "ni_yoy_growth": 0.3471,
    "rev_yoy_growth": 0.2317,
    "ni_qoq_growth": -0.2116,
    "ni_acceleration": -0.867,
    "price_on_event_date": 41.66,
    "price_5d_after": 49.75,
    "price_20d_after": 55.4,
    "earn_ret_5d": 0.1775,
    "earn_ret_5d_to_20d": 0.1076
  },
  {
    "ticker": "ELF",
    "period": "Q1 2023",
    "announcement_date": null,
    "filing_date": "2022-08-04",
    "event_date": "2022-08-04",
    "eps_estimate": null,
    "eps_actual": null,
    "eps_surprise_pct": null,
    "revenue": 122601000.0,
    "net_income": 14469000.0,
    "shares_outstanding": 53834732.0,
    "ni_yoy_growth": 1.2141,
    "rev_yoy_growth": 0.3252,
    "ni_qoq_growth": 0.8452,
    "ni_acceleration": -1.4179,
    "price_on_event_date": 36.18,
    "price_5d_after": 36.41,
    "price_20d_after": 38.44,
    "earn_ret_5d": 0.0063,
    "earn_ret_5d_to_20d": 0.0543
  },
  {
    "ticker": "ELF",
    "period": "Q3 2022",
    "announcement_date": null,
    "filing_date": "2022-02-03",
    "event_date": "2022-02-03",
    "eps_estimate": null,
    "eps_actual": null,
    "eps_surprise_pct": null,
    "revenue": 98118000.0,
    "net_income": 6214000.0,
    "shares_outstanding": 53891438.0,
    "ni_yoy_growth": 2.632,
    "rev_yoy_growth": 0.3047,
    "ni_qoq_growth": 0.0821,
    "ni_acceleration": 1.3008,
    "price_on_event_date": 28.52,
    "price_5d_after": 27.84,
    "price_20d_after": 25.12,
    "earn_ret_5d": -0.0241,
    "earn_ret_5d_to_20d": -0.1028
  },
  {
    "ticker": "ELF",
    "period": "Q2 2022",
    "announcement_date": null,
    "filing_date": "2021-11-04",
    "event_date": "2021-11-04",
    "eps_estimate": null,
    "eps_actual": null,
    "eps_surprise_pct": null,
    "revenue": 91855000.0,
    "net_income": 5724000.0,
    "shares_outstanding": 53541724.0,
    "ni_yoy_growth": 1.3312,
    "rev_yoy_growth": 0.3531,
    "ni_qoq_growth": -0.3687,
    "ni_acceleration": 1.2975,
    "price_on_event_date": 30.21,
    "price_5d_after": 31.24,
    "price_20d_after": 30.15,
    "earn_ret_5d": 0.0335,
    "earn_ret_5d_to_20d": -0.0355
  },
  {
    "ticker": "ELF",
    "period": "Q1 2022",
    "announcement_date": null,
    "filing_date": "2021-08-05",
    "event_date": "2021-08-05",
    "eps_estimate": null,
    "eps_actual": null,
    "eps_surprise_pct": null,
    "revenue": 97047000.0,
    "net_income": 8276000.0,
    "shares_outstanding": 53408443.0,
    "ni_yoy_growth": 0.0337,
    "rev_yoy_growth": 0.1837,
    "ni_qoq_growth": 0.6554,
    "ni_acceleration": 0.4502,
    "price_on_event_date": 29.83,
    "price_5d_after": 29.72,
    "price_20d_after": 31.05,
    "earn_ret_5d": -0.0037,
    "earn_ret_5d_to_20d": 0.0438
  },
  {
    "ticker": "ELF",
    "period": "Q3 2021",
    "announcement_date": null,
    "filing_date": "2021-02-04",
    "event_date": "2021-02-04",
    "eps_estimate": null,
    "eps_actual": null,
    "eps_surprise_pct": null,
    "revenue": 88562000.0,
    "net_income": 4297000.0,
    "shares_outstanding": 52335821.0,
    "ni_yoy_growth": -0.4165,
    "rev_yoy_growth": 0.2699,
    "ni_qoq_growth": 2.2631,
    "ni_acceleration": 1.6986,
    "price_on_event_date": 23.12,
    "price_5d_after": 23.28,
    "price_20d_after": 25.78,
    "earn_ret_5d": 0.0069,
    "earn_ret_5d_to_20d": 0.102
  },
  {
    "ticker": "ELF",
    "period": "Q2 2021",
    "announcement_date": null,
    "filing_date": "2020-11-05",
    "event_date": "2020-11-05",
    "eps_estimate": null,
    "eps_actual": null,
    "eps_surprise_pct": null,
    "revenue": 72350000.0,
    "net_income": 447000.0,
    "shares_outstanding": 51748437.0,
    "ni_yoy_growth": -2.1151,
    "rev_yoy_growth": 0.1911,
    "ni_qoq_growth": -1.2186,
    "ni_acceleration": null,
    "price_on_event_date": 19.43,
    "price_5d_after": 21.1,
    "price_20d_after": 22.36,
    "earn_ret_5d": 0.0825,
    "earn_ret_5d_to_20d": 0.058
  },
  {
    "ticker": "ELF",
    "period": "Q1 2021",
    "announcement_date": null,
    "filing_date": "2020-08-06",
    "event_date": "2020-08-06",
    "eps_estimate": null,
    "eps_actual": null,
    "eps_surprise_pct": null,
    "revenue": 64527000.0,
    "net_income": 1512000.0,
    "shares_outstanding": 50939938.0,
    "ni_yoy_growth": null,
    "rev_yoy_growth": -0.0247,
    "ni_qoq_growth": -1.6663,
    "ni_acceleration": null,
    "price_on_event_date": 20.54,
    "price_5d_after": 20.14,
    "price_20d_after": 19.37,
    "earn_ret_5d": -0.0197,
    "earn_ret_5d_to_20d": -0.039
  },
  {
    "ticker": "ELF",
    "period": "Q3 2020",
    "announcement_date": null,
    "filing_date": "2020-02-06",
    "event_date": "2020-02-06",
    "eps_estimate": null,
    "eps_actual": null,
    "eps_surprise_pct": null,
    "revenue": 80760000.0,
    "net_income": 8002000.0,
    "shares_outstanding": 50966550.0,
    "ni_yoy_growth": 0.7149,
    "rev_yoy_growth": 0.2343,
    "ni_qoq_growth": 0.2053,
    "ni_acceleration": -0.938,
    "price_on_event_date": 18.93,
    "price_5d_after": 19.84,
    "price_20d_after": 15.65,
    "earn_ret_5d": 0.047,
    "earn_ret_5d_to_20d": -0.2372
  },
  {
    "ticker": "ELF",
    "period": "Q2 2020",
    "announcement_date": null,
    "filing_date": "2019-11-07",
    "event_date": "2019-11-07",
    "eps_estimate": null,
    "eps_actual": null,
    "eps_surprise_pct": null,
    "revenue": 67615000.0,
    "net_income": 6517000.0,
    "shares_outstanding": 50939915.0,
    "ni_yoy_growth": 1.6529,
    "rev_yoy_growth": 0.1354,
    "ni_qoq_growth": 0.5645,
    "ni_acceleration": -0.0281,
    "price_on_event_date": 17.29,
    "price_5d_after": 16.39,
    "price_20d_after": 15.26,
    "earn_ret_5d": -0.0535,
    "earn_ret_5d_to_20d": -0.0714
  },
  {
    "ticker": "ELF",
    "period": "Q1 2020",
    "announcement_date": null,
    "filing_date": "2019-08-08",
    "event_date": "2019-08-08",
    "eps_estimate": null,
    "eps_actual": null,
    "eps_surprise_pct": null,
    "revenue": 59764000.0,
    "net_income": 3706000.0,
    "shares_outstanding": 50317088.0,
    "ni_yoy_growth": 1.681,
    "rev_yoy_growth": -0.098,
    "ni_qoq_growth": -1.5756,
    "ni_acceleration": null,
    "price_on_event_date": 17.31,
    "price_5d_after": 16.41,
    "price_20d_after": 17.52,
    "earn_ret_5d": -0.0534,
    "earn_ret_5d_to_20d": 0.0655
  },
  {
    "ticker": "ELF",
    "period": "Q1 2019",
    "announcement_date": null,
    "filing_date": "2019-05-09",
    "event_date": "2019-05-09",
    "eps_estimate": null,
    "eps_actual": null,
    "eps_surprise_pct": null,
    "revenue": 66141000.0,
    "net_income": -17914000.0,
    "shares_outstanding": 48022926.0,
    "ni_yoy_growth": null,
    "rev_yoy_growth": -0.083,
    "ni_qoq_growth": -1.5208,
    "ni_acceleration": null,
    "price_on_event_date": 11.47,
    "price_5d_after": 12.14,
    "price_20d_after": 11.91,
    "earn_ret_5d": 0.0568,
    "earn_ret_5d_to_20d": -0.0191
  },
  {
    "ticker": "ELF",
    "period": "Q3 2018",
    "announcement_date": null,
    "filing_date": "2018-11-06",
    "event_date": "2018-11-06",
    "eps_estimate": null,
    "eps_actual": null,
    "eps_surprise_pct": null,
    "revenue": 63889000.0,
    "net_income": 3915000.0,
    "shares_outstanding": 49123703.0,
    "ni_yoy_growth": -0.014,
    "rev_yoy_growth": 0.1344,
    "ni_qoq_growth": 1.1433,
    "ni_acceleration": 0.5346,
    "price_on_event_date": 13.23,
    "price_5d_after": 12.98,
    "price_20d_after": 11.21,
    "earn_ret_5d": -0.0191,
    "earn_ret_5d_to_20d": -0.1466
  },
  {
    "ticker": "ELF",
    "period": "Q2 2018",
    "announcement_date": null,
    "filing_date": "2018-08-09",
    "event_date": "2018-08-09",
    "eps_estimate": null,
    "eps_actual": null,
    "eps_surprise_pct": null,
    "revenue": 59055000.0,
    "net_income": 1248000.0,
    "shares_outstanding": 49425927.0,
    "ni_yoy_growth": -0.5486,
    "rev_yoy_growth": -0.0254,
    "ni_qoq_growth": 0.5926,
    "ni_acceleration": null,
    "price_on_event_date": 9.85,
    "price_5d_after": 11.25,
    "price_20d_after": 13.54,
    "earn_ret_5d": 0.1329,
    "earn_ret_5d_to_20d": 0.1853
  },
  {
    "ticker": "ELF",
    "period": "Q1 2018",
    "announcement_date": null,
    "filing_date": "2018-05-10",
    "event_date": "2018-05-10",
    "eps_estimate": null,
    "eps_actual": null,
    "eps_surprise_pct": null,
    "revenue": 65920000.0,
    "net_income": 690000.0,
    "shares_outstanding": 49302771.0,
    "ni_yoy_growth": null,
    "rev_yoy_growth": 0.1575,
    "ni_qoq_growth": -2.1401,
    "ni_acceleration": null,
    "price_on_event_date": 19.27,
    "price_5d_after": 19.99,
    "price_20d_after": 19.33,
    "earn_ret_5d": 0.0367,
    "earn_ret_5d_to_20d": -0.0336
  },
  {
    "ticker": "ELF",
    "period": "Q3 2017",
    "announcement_date": null,
    "filing_date": "2017-11-09",
    "event_date": "2017-11-09",
    "eps_estimate": null,
    "eps_actual": null,
    "eps_surprise_pct": null,
    "revenue": 71865000.0,
    "net_income": 5865000.0,
    "shares_outstanding": 49283247.0,
    "ni_yoy_growth": null,
    "rev_yoy_growth": null,
    "ni_qoq_growth": 0.3902,
    "ni_acceleration": null,
    "price_on_event_date": 18.91,
    "price_5d_after": 19.57,
    "price_20d_after": 21.83,
    "earn_ret_5d": 0.0343,
    "earn_ret_5d_to_20d": 0.1093
  },
  {
    "ticker": "ELF",
    "period": "Q2 2017",
    "announcement_date": null,
    "filing_date": "2017-08-11",
    "event_date": "2017-08-11",
    "eps_estimate": null,
    "eps_actual": null,
    "eps_surprise_pct": null,
    "revenue": 55856000.0,
    "net_income": 3970000.0,
    "shares_outstanding": 49509940.0,
    "ni_yoy_growth": null,
    "rev_yoy_growth": null,
    "ni_qoq_growth": 0.6087,
    "ni_acceleration": null,
    "price_on_event_date": 25.19,
    "price_5d_after": 23.01,
    "price_20d_after": 20.01,
    "earn_ret_5d": -0.0905,
    "earn_ret_5d_to_20d": -0.1397
  },
  {
    "ticker": "ELF",
    "period": "Q1 2017",
    "announcement_date": null,
    "filing_date": "2017-05-12",
    "event_date": "2017-05-12",
    "eps_estimate": null,
    "eps_actual": null,
    "eps_surprise_pct": null,
    "revenue": 60574000.0,
    "net_income": 2160000.0,
    "shares_outstanding": 49477874.0,
    "ni_yoy_growth": null,
    "rev_yoy_growth": null,
    "ni_qoq_growth": -0.0957,
    "ni_acceleration": null,
    "price_on_event_date": 27.03,
    "price_5d_after": 25.12,
    "price_20d_after": 25.28,
    "earn_ret_5d": -0.0733,
    "earn_ret_5d_to_20d": 0.0063
  },
  {
    "ticker": "ELF",
    "period": "Q3 2016",
    "announcement_date": null,
    "filing_date": "2016-11-14",
    "event_date": "2016-11-14",
    "eps_estimate": null,
    "eps_actual": null,
    "eps_surprise_pct": null,
    "revenue": 56312000.0,
    "net_income": -2377000.0,
    "shares_outstanding": 5109016.0,
    "ni_yoy_growth": null,
    "rev_yoy_growth": null,
    "ni_qoq_growth": null,
    "ni_acceleration": null,
    "price_on_event_date": 29.37,
    "price_5d_after": 30.32,
    "price_20d_after": 30.24,
    "earn_ret_5d": 0.0318,
    "earn_ret_5d_to_20d": -0.0026
  }
]